Metadata-Version: 2.4
Name: meta-ads-mcp
Version: 1.0.20
Summary: Model Context Protocol (MCP) server for Meta Ads - Use Remote MCP at pipeboard.co for easiest setup
Project-URL: Homepage, https://github.com/pipeboard-co/meta-ads-mcp
Project-URL: Bug Tracker, https://github.com/pipeboard-co/meta-ads-mcp/issues
Author-email: Yves Junqueira <yves.junqueira@gmail.com>
License: BUSL-1.1
License-File: LICENSE
Keywords: ads,api,claude,facebook,mcp,meta
Classifier: License :: Other/Proprietary License
Classifier: Operating System :: OS Independent
Classifier: Programming Language :: Python :: 3
Requires-Python: >=3.10
Requires-Dist: httpx>=0.26.0
Requires-Dist: mcp[cli]==1.12.2
Requires-Dist: pathlib>=1.0.1
Requires-Dist: pillow>=10.0.0
Requires-Dist: pytest-asyncio>=1.0.0
Requires-Dist: pytest>=8.4.1
Requires-Dist: python-dateutil>=2.8.2
Requires-Dist: python-dotenv>=1.1.0
Requires-Dist: requests>=2.32.3
